xep/__init__.py
xep/block.py
xep/geometry.py
xep/loop.py
xep/new.py
xep/report.py
xep/table.py
xep/worksheet.py
xep/template/__init__.py
xep/template/cell.py
xep/template/format.py
xep/template/range.py
xep-0.3.dist-info/LICENSE
xep-0.3.dist-info/METADATA
xep-0.3.dist-info/WHEEL
xep-0.3.dist-info/top_level.txt
xep-0.3.dist-info/RECORD
