Metadata-Version: 2.1
Name: xep
Version: 0.3
Home-page: https://github.com/Onanim90/xep
Author: Pavel Ilyin
Author-email: azunya.90@gmail.com
Classifier: Programming Language :: Python :: 3.9
Classifier: Programming Language :: Python :: 3 :: Only
Classifier: License :: OSI Approved :: MIT License
Classifier: Operating System :: OS Independent
Requires-Python: >=3.9
License-File: LICENSE
Requires-Dist: openpyxl
Requires-Dist: pyyaml
